{"manifestVersion":"1.1","info":{"id":"Microsoft.VisualStudio.JavaScript.DebugAdapter,version=1.1.45,productarch=neutral"},"packages":[{"id":"Microsoft.VisualStudio.JavaScript.DebugAdapter","version":"1.1.45","type":"Vsix","productArch":"neutral","payloads":[{"fileName":"Microsoft.VisualStudio.JavaScript.DebugAdapter.vsix","size":12148279}],"vsixId":"Microsoft.VisualStudio.JavaScript.DebugAdapter.cde3ffb3-2b8d-4776-b1d9-ff645a8f11ca","extensionDir":"[installdir]\\Common7\\IDE\\CommonExtensions\\Microsoft\\JSDiagnostics\\Debugger","installSizes":{"targetDrive":64333130}}]}