{"manifestVersion":"1.1","info":{"id":"Microsoft.VisualStudio.Containers.Tools.Extensions,version=17.0.2308.2901,productarch=neutral"},"packages":[{"id":"Microsoft.VisualStudio.Containers.Tools.Extensions","version":"17.0.2308.2901","type":"Vsix","productArch":"neutral","payloads":[{"fileName":"Microsoft.VisualStudio.Containers.Tools.Extensions.Vsix.vsix","size":1754448}],"vsixId":"Microsoft.VisualStudio.Containers.Tools.Extensions","extensionDir":"[installdir]\\Common7\\IDE\\Extensions\\y1pwplxh.2oy","installSizes":{"targetDrive":4634715}}]}